FishProcessManagement/__init__.py
FishProcessManagement/child.py
FishProcessManagement/main.py
FishProcessManagement/test.py
FishProcessManagement-2023.5.23.8.dist-info/METADATA
FishProcessManagement-2023.5.23.8.dist-info/WHEEL
FishProcessManagement-2023.5.23.8.dist-info/top_level.txt
FishProcessManagement-2023.5.23.8.dist-info/RECORD
