Metadata-Version: 2.1
Name: FishProcessManagement
Version: 2023.5.23.8
Summary: 一个后台项目管理器，适用于启动或关闭多个毫不相关的项目，注意他不是函数，只允许启动时指定程序的位置
Home-page: https://space.bilibili.com/698117971?spm_id_from=333.1007.0.0
Author: FishProcessManagement
Author-email: 2645602049@qq.com
